{
  "welcomeTitle": "ব্যয় পর্যবেক্ষণ করুন, বাজেট বজায় রাখুন—ExpenseMate।",
  "welcomeSubtitle": "আয় বুদ্ধিমত্তার সাথে ভাগ করুন ExpenseMate-এর মাধ্যমে।",
  "continueButton": "চালিয়ে যান",
  "settings": "সেটিংস",
  "setMonthlyBudget": "মাসিক বাজেট নির্ধারণ করুন",
  "removeBudget": "বাজেট মুছুন",
  "budgetRemoved": "মাসিক বাজেট সফলভাবে মুছে ফেলা হয়েছে",
  "noBudgetSet": "কোনো বাজেট সেট করা হয়নি",
  "enableNotifications": "নোটিফিকেশন চালু করুন",
  "disableNotifications": "নোটিফিকেশন বন্ধ করুন",
  "changePassword": "পাসওয়ার্ড পরিবর্তন করুন",
  "setUpdatePin": "পিন সেট বা আপডেট করুন",
  "removePin": "পিন মুছুন",
  "resetAllData": "সব তথ্য রিসেট করুন",
  "language": "ভাষা",
  "cancel": "বাতিল",
  "save": "সংরক্ষণ করুন",
  "yes": "হ্যাঁ",
  "confirmReset": "রিসেট নিশ্চিত করুন",
  "confirmResetDescription": "আপনি কি নিশ্চিতভাবে প্রোফাইল রিসেট করতে চান?",
  "pinSuccess": "পিন সফলভাবে সংরক্ষিত হয়েছে!",
  "pinRemoved": "পিন মুছে ফেলা হয়েছে।",
  "noPinSet": "কোনো পিন সেট করা নেই।",
  "invalidPin": "দয়া করে একটি বৈধ ৪-সংখ্যার পিন দিন",
  "budgetUpdated": "বাজেট সফলভাবে আপডেট হয়েছে!",
  "notificationsEnabled": "নোটিফিকেশন চালু হয়েছে",
  "notificationsDisabled": "নোটিফিকেশন বন্ধ হয়েছে",
  "passwordChanged": "পাসওয়ার্ড সফলভাবে পরিবর্তন হয়েছে! (ডেমো)",
  "today": "আজ",
  "week": "সপ্তাহ",
  "month": "মাস",
  "year": "বছর",
  "accountBalance": "অ্যাকাউন্ট ব্যালেন্স",
  "monthlyBudget": "মাসিক বাজেট",
  "remaining": "অবশিষ্ট",
  "budgetExceeded": "আপনি মাসিক বাজেট ছাড়িয়ে গেছেন!",
  "income": "আয়",
  "expenses": "ব্যয়",
  "expense": "ব্যয়",
  "recentTransactions": "সাম্প্রতিক লেনদেন",
  "viewAll": "সব দেখুন",
  "noTransactions": "এখনও কোনো লেনদেন নেই",
  "home": "হোম",
  "transactions": "লেনদেন",
  "statistics": "পরিসংখ্যান",
  "profile": "প্রোফাইল",
  "addTransaction": "লেনদেন যোগ করুন",
  "howMuch": "কত টাকা?",
  "enterAmount": "টাকা লিখুন",
  "category": "বিভাগ",
  "description": "বিবরণ",
  "date": "তারিখ",
  "transactionSaved": "লেনদেন সফলভাবে সংরক্ষিত হয়েছে!",
  "invalidAmount": "অবৈধ পরিমাণ দেওয়া হয়েছে",
  "allFieldsRequired": "সব ফিল্ড পূরণ করা আবশ্যক",
  "transactionHistory": "লেনদেনের ইতিহাস",
  "searchHint": "বিভাগ, নোট বা টাকার পরিমাণ দিয়ে অনুসন্ধান করুন",
  "editTransaction": "লেনদেন সম্পাদনা করুন",
  "amount": "টাকা",
  "note": "নোট",
  "updateFailed": "আপডেট ব্যর্থ হয়েছে",
  "pleaseEnterValidAmount": "একটি বৈধ টাকার পরিমাণ লিখুন",
  "noTransactionsAvailable": "কোনো লেনদেন নেই",
  "showing": "দেখানো হচ্ছে",
  "transactionsAll": "সব",
  "category_food": "খাবার",
  "category_shopping": "শপিং",
  "category_fuel": "জ্বালানি",
  "category_salary": "বেতন",
  "category_subscription": "সাবস্ক্রিপশন",
  "category_grocery": "মুদিখানা",
  "category_personal": "ব্যক্তিগত",
  "category_travel": "ভ্রমণ",
  "category_medicine": "ঔষধ",
  "category_entertainment": "বিনোদন",
  "category_bills": "বিল",
  "category_education": "শিক্ষা",
  "category_investment": "বিনিয়োগ",
  "category_others": "অন্যান্য",
  "editInfo": "তথ্য সম্পাদনা করুন",
  "exportAsPdf": "PDF হিসেবে রপ্তানি",
  "resetProfile": "প্রোফাইল রিসেট করুন",
  "logout": "লগআউট",
  "tapToChangePhoto": "ছবি পরিবর্তন করতে আলতো চাপুন",
  "confirmResetTitle": "রিসেট নিশ্চিত করুন",
  "confirm": "নিশ্চিত করুন",
  "profileResetSuccess": "প্রোফাইল সফলভাবে রিসেট হয়েছে",
  "pdfGeneratedSuccess": "PDF তৈরি হয়েছে এবং শেয়ার অপশন দেখানো হয়েছে",
  "pdfGenerationFailed": "PDF তৈরি করতে ব্যর্থ হয়েছে",
  "pinRequired": "পিন প্রয়োজন",
  "enterPin": "আপনার ৪ সংখ্যার পিন লিখুন",
  "incorrectPin": "পিন ভুল হয়েছে",
  "weeklyReport": "সাপ্তাহিক প্রতিবেদন",
  "weekLabel": "সপ্তাহ",
  "weeklyIncome": "সাপ্তাহিক আয়",
  "weeklyExpense": "সাপ্তাহিক ব্যয়",
  "incomeLabel": "আয়",
  "expenseLabel": "ব্যয়",
  "noData": "কোনো তথ্য পাওয়া যায়নি",
  "balance": "ব্যালেন্স",
  "balanceSummary": "ব্যালেন্স সারসংক্ষেপ",
  "error": "ত্রুটি",
  "success": "সফল",
  "errorSavingTransaction": "লেনদেন সংরক্ষণ করতে ব্যর্থ হয়েছে। আবার চেষ্টা করুন।"
}
